{
 "actions": [],
 "allow_rename": 1,
 "creation": "2024-10-08 13:03:47.235070",
 "doctype": "DocType",
 "editable_grid": 1,
 "engine": "InnoDB",
 "field_order": [
  "purchase_invoice",
  "item",
  "accepted_qty",
  "rate",
  "amount"
 ],
 "fields": [
  {
   "fieldname": "purchase_invoice",
   "fieldtype": "Link",
   "label": "Purchase Invoice",
   "options": "Purchase Invoice"
  },
  {
   "fieldname": "item",
   "fieldtype": "Data",
   "label": "Item"
  },
  {
   "fieldname": "accepted_qty",
   "fieldtype": "Float",
   "label": "Accepted Qty"
  },
  {
   "fieldname": "rate",
   "fieldtype": "Currency",
   "label": "Rate"
  },
  {
   "fieldname": "amount",
   "fieldtype": "Currency",
   "label": "Amount"
  }
 ],
 "index_web_pages_for_search": 1,
 "istable": 1,
 "links": [],
 "modified": "2024-10-08 15:24:58.390203",
 "modified_by": "Administrator",
 "module": "Upande Vf Custom",
 "name": "VF Asset Repair Purchase Invoices",
 "owner": "Administrator",
 "permissions": [],
 "sort_field": "modified",
 "sort_order": "DESC",
 "states": []
}